verilog/mem.v
module mem (
    icode, ifun, valE, valA, valP, valM, memdata
);
input [3:0] icode;
input [3:0] ifun;
input [63:0] valE;
input [63:0] valA;
input [63:0] valP;
output reg [63:0] valM;
output reg [63:0] memdata;

reg [63:0] data[0:1023];

initial begin
    for (integer i = 0; i < 1024; i++)
    begin
         data[i] = 64'b111; 
    end
end

always @(*) 
begin
    if (icode == 4'd4)
        data[valE] = valA;
    if (icode == 4'd5)
        valM = data[valE];
    if (icode == 4'd8) 
        data[valE] = valP;
    if (icode == 4'd9)
        valM = data[valA];
    if (icode == 4'd10)
        data[valE] = valA;
    if (icode == 4'd11)
        valM = data[valE];
    
    memdata = data[valE];
end

endmodule

verilog/mem_tb.v
`timescale 10ns/1ps

module mem_tb;

initial begin
    $dumpfile("mem_tb.vcd");
    $dumpvars(0, mem_tb);
end

reg [3:0] icode;
reg [3:0] ifun;
reg signed [63:0] valE;
reg signed [63:0] valA;
reg signed [63:0] valP;
wire signed [63:0] valM;
wire signed [63:0] memdata;

mem m1
(
    .icode(icode),
    .ifun(ifun),
    .valE(valE),
    .valA(valA),
    .valP(valP),
    .valM(valM),
    .memdata(memdata)
);

initial begin
    icode = 4'd0; ifun = 4'd0; valE = 64'd0; valA = 64'd0; valP = 64'd0;
    #10;
    icode = 4'd1; ifun = 4'd0; valA = 64'd10; valE = 64'd10; valP = 64'd10;
    #10;
    icode = 4'd2; ifun = 4'd0;
    #10;
    icode = 4'd3; ifun = 4'd0;
    #10;
    icode = 4'd4; ifun = 4'd0;
    #10;
    icode = 4'd5; ifun = 4'd0;
    #10;
    icode = 4'd6; ifun = 4'd0;
    #10;
    icode = 4'd7; ifun = 4'd0;
    #10;
    icode = 4'd8; ifun = 4'd0;
    #10;
    icode = 4'd9; ifun = 4'd0;
    #10;
    icode = 4'd10; ifun = 4'd0;
    #10;
    icode = 4'd11; ifun = 4'd0;
end

initial
begin
    $monitor("icode = %d, ifun = %d, valA = %d, valE = %d, valP = %d, memdata = %d, valM = %d", icode, ifun, valA, valE, valP, memdata, valM);
end
endmodule

verilog/mem_tb.vcd
$date
	Thu Feb 16 21:08:07 2023
$end
$version
	Icarus Verilog
$end
$timescale
	1ps
$end
$scope module mem_tb $end
$var wire 64 ! valM [63:0] $end
$var wire 64 " memdata [63:0] $end
$var reg 4 # icode [3:0] $end
$var reg 4 $ ifun [3:0] $end
$var reg 64 % valA [63:0] $end
$var reg 64 & valE [63:0] $end
$var reg 64 ' valP [63:0] $end
$scope module m1 $end
$var wire 4 ( icode [3:0] $end
$var wire 4 ) ifun [3:0] $end
$var wire 64 * valA [63:0] $end
$var wire 64 + valE [63:0] $end
$var wire 64 , valP [63:0] $end
$var reg 64 - memdata [63:0] $end
$var reg 64 . valM [63:0] $end
$scope begin $ivl_for_loop0 $end
$var integer 32 / i [31:0] $end
$upscope $end
$upscope $end
$upscope $end
$enddefinitions $end
#0
$dumpvars
b10000000000 /
bx .
b111 -
b0 ,
b0 +
b0 *
b0 )
b0 (
b0 '
b0 &
b0 %
b0 $
b0 #
b111 "
bx !
$end
#100000
b1010 '
b1010 ,
b1010 &
b1010 +
b1010 %
b1010 *
b1 #
b1 (
#200000
b10 #
b10 (
#300000
b11 #
b11 (
#400000
b1010 "
b1010 -
b100 #
b100 (
#500000
b1010 !
b1010 .
b101 #
b101 (
#600000
b110 #
b110 (
#700000
b111 #
b111 (
#800000
b1000 #
b1000 (
#900000
b1001 #
b1001 (
#1000000
b1010 #
b1010 (
#1100000
b1011 #
b1011 (
